linein/__init__.py
linein/exceptions.py
linein/loader.py
linein/registry.py
linein/source.py
linein-0.0.8.dist-info/LICENSE
linein-0.0.8.dist-info/METADATA
linein-0.0.8.dist-info/WHEEL
linein-0.0.8.dist-info/top_level.txt
linein-0.0.8.dist-info/RECORD
