Metadata-Version: 2.1
Name: linein
Version: 0.0.8
Summary: a helper lib for easily loading sample data into django models.
Home-page: https://github.com/claydodo/linein
Author: claydodo
Author-email: claydodo@foxmail.com
License: UNKNOWN
Project-URL: Bug Tracker, https://github.com/claydodo/linein/issues
Platform: UNKNOWN
Classifier: Programming Language :: Python :: 3
Classifier: License :: OSI Approved :: The Unlicense (Unlicense)
Classifier: Operating System :: OS Independent
Requires-Python: >=3.0
License-File: LICENSE
